{
  "site-title": "BarcelonaJS",
  "navbar": [
    {
      "label": "Code of Conduct",
      "href": "/code"
    },
    {
      "label": "About",
      "href": "/about"
    },
    {
      "label": "Home",
      "href": "/"
    }
  ],
  "teams": [
    {
      "label": "CoreJS",
      "members": [
        {
          "name": "Patrick Heneise",
          "twitter": "PatrickHeneise",
          "portrait": "assets/team/patrick.jpg",
          "email": "patrick@barcelonajs.org",
          "bio": "Co-Founder of BarcelonaJS.org. Works at blended.io."
        },
        {
          "name": "Jean-Carlos Meninno",
          "twitter": "eth0lo",
          "email": "jean@barcelonajs.org",
          "bio": "Co-Founder of BarcelonaJS.org."
        },
        {
          "name": "Isabel Cabezas",
          "twitter": "isabelcabezasm",
          "portrait": "assets/team/isabel.jpg",
          "email": "isabel@barcelonajs.org"
        }
      ]
    }
  ]
}
